kalabash_stats/__init__.py
kalabash_stats/apps.py
kalabash_stats/forms.py
kalabash_stats/graphics.py
kalabash_stats/handlers.py
kalabash_stats/kalmonak_extension.py
kalabash_stats/lib.py
kalabash_stats/signals.py
kalabash_stats/urls.py
kalabash_stats/views.py
kalabash_stats/locale/en/LC_MESSAGES/django.mo
kalabash_stats/locale/en/LC_MESSAGES/django.po
kalabash_stats/locale/en/LC_MESSAGES/djangojs.mo
kalabash_stats/locale/en/LC_MESSAGES/djangojs.po
kalabash_stats/locale/fr/LC_MESSAGES/django.mo
kalabash_stats/locale/fr/LC_MESSAGES/django.po
kalabash_stats/locale/fr/LC_MESSAGES/djangojs.mo
kalabash_stats/locale/fr/LC_MESSAGES/djangojs.po
kalabash_stats/management/__init__.py
kalabash_stats/management/commands/__init__.py
kalabash_stats/management/commands/logparser.py
kalabash_stats/management/commands/update_statistics.py
kalabash_stats/static/kalabash_stats/css/stats.css
kalabash_stats/static/kalabash_stats/js/d3.legend.js
kalabash_stats/static/kalabash_stats/js/graphic.js
kalabash_stats/static/kalabash_stats/js/stats.js
kalabash_stats/templates/kalabash_stats/index.html
kalabash_stats/tests/__init__.py
kalabash_stats/tests/mail.log
kalabash_stats/tests/test_views.py
kalabash_stats-1.4.11.dist-info/LICENSE
kalabash_stats-1.4.11.dist-info/METADATA
kalabash_stats-1.4.11.dist-info/WHEEL
kalabash_stats-1.4.11.dist-info/top_level.txt
kalabash_stats-1.4.11.dist-info/RECORD
